{
  "schema_version": 1,
  "id": "82dbd905-9f73-4f70-b8c9-ee7c89b34960",
  "receipt_type": "approved",
  "verdict": "approved",
  "reviewer": {
    "agent": "curator"
  },
  "reviewed_at": "2026-06-09T16:34:58.802Z",
  "scope_fingerprint": {
    "hash": "537c7193cd39557f7667e29accb141986219070bd1cebf06e317c57a3f2aa3c6",
    "scope_description": "curator-init-briefing",
    "content_length": 2853
  },
  "checked_aspects": [
    "knowledge_entries",
    "prior_phase_summaries",
    "contradiction_detection"
  ],
  "validated_claims": [
    "knowledge_entries_reviewed: 0",
    "prior_phases_covered: 0",
    "contradictions: 0"
  ]
}